{"title":"Letter CLIII. To Aetius, Presbyter ,of Constantinople.","code":"npnf2_12_npnf2_12_151_letter_cliii_to_aetius_presbyter_of_constantinople_","author":false,"filename":"sources/www.tertullian.org/fathers2/NPNF2-12/Npnf2-12-151.htm","chapters":[{"name":"","index":1,"paragraphs":[{"text":"","index":"0","references":[]},{"text":"Letter CLIII. To Aetius, Presbyter ,of Constantinople.","index":"1","references":[]},{"text":"(Asking him to assist in the distribution of these letters.)","index":"2","references":[]},{"text":"","index":"3","references":[]},{"text":"","index":"4","references":[]}]}]}