{"title":"Letters LV to LVIII.","code":"npnf2_12_npnf2_12_60_letters_lv_to_lviii_","author":false,"filename":"sources/www.tertullian.org/fathers2/NPNF2-12/Npnf2-12-60.htm","chapters":[{"name":"","index":1,"paragraphs":[{"text":"","index":"0","references":[]},{"text":"Letters LV to LVIII.","index":"1","references":[]},{"text":"A series of Letters.","index":"2","references":[]},{"text":"(1) From Valentinian the Emperor to Theodosius Augustus.","index":"3","references":[]},{"text":"(2) From Galla Placidia Augusta to Theodosius Augustus.","index":"4","references":[]},{"text":"(3) From Licinia Eudoxia Augusta to Theodosius Augustus.","index":"5","references":[]},{"text":"(4) From Galla Placidia Augusta to Pulcheria Augusta, all graphically describing how Leo had appealed to them in public to press his suit with Theodosius. Of these, LVI. is subjoined as perhaps the most interesting specimen.","index":"6","references":[]},{"text":"","index":"7","references":[]},{"text":"","index":"8","references":[]}]}]}