[{"chapter":22,"verse":17,"source_code":"npnf2_10_npnf2_10_24_book_ii_","source_chapter":7,"source_paragraph":"72","folder":"NPNF2-10","text":"42. The words, you say, are the words of Christ. True-consider, though, the occasion of His speaking them, and in what character He speaks. He hath taken upon Him the substance of man,[fn-44-P4466_1150160:61-nf] and therewith its affections. Again, you find in the place above cited, that \"He went forward a little further, and fell on His face, praying, and saying: Father, if it be possible.\"[fn-44-P4467_1150402:62-nf] Not as God, then, but as man, speaketh He, for could God be ignorant of the possibility or impossibility of aught? Or is anything impossible for God, when the Scripture saith: \"For Thee nothing is impossible\"?[fn-44-P4468_1150653:63-nf] ","title":"Book II.","author":"St. Ambrose"}]