{"title":"The Life of the Blessed Emperor Constantine","code":"npnf2_01_npnf2_01_23_the_life_of_the_blessed_emperor_constantine","author":"Eusebius Pamphilus","filename":"sources/www.tertullian.org/fathers2/NPNF2-01/Npnf2-01-23.htm","chapters":[{"name":"","index":1,"paragraphs":[{"text":"","index":"0","references":[]},{"text":"The Life of the Blessed Emperor Constantine","index":"1","references":[]},{"text":"By Eusebius,","index":"2","references":[]},{"text":"Together with the","index":"3","references":[]},{"text":"Oration of Constantine to the Assembly of the Saints,","index":"4","references":[]},{"text":"And the","index":"5","references":[]},{"text":"Oration of Eusebius in Praise of Constantine.","index":"6","references":[]},{"text":"\nBy Eusebius,","index":"7","references":[]},{"text":"\nTogether with the","index":"8","references":[]},{"text":"\nOration of Constantine to the Assembly of the Saints,","index":"9","references":[]},{"text":"\nAnd the","index":"10","references":[]},{"text":"\nOration of Eusebius in Praise of Constantine.","index":"11","references":[]},{"text":"A Revised Translation, with Prolegomena and Notes, by Ernest Cushing Richardson, Phd., Librarian and Associate Professor in Hartford Theological Seminary.   ","index":"12","references":[]},{"text":"","index":"13","references":[]},{"text":"","index":"14","references":[]}]}]}